constants.py
pyspt.py
pythonspt-1.0.0b3.dist-info/LICENSE
pythonspt-1.0.0b3.dist-info/METADATA
pythonspt-1.0.0b3.dist-info/WHEEL
pythonspt-1.0.0b3.dist-info/entry_points.txt
pythonspt-1.0.0b3.dist-info/top_level.txt
pythonspt-1.0.0b3.dist-info/RECORD
