Metadata-Version: 2.1
Name: pythonspt
Version: 1.0.0b3
Summary: Simple pomodoro timer written in Python
Home-page: https://github.com/irizwaririz/pyspt
Author: John Carlo Roberto
Author-email: 10111643+Irizwaririz@users.noreply.github.com
Keywords: console,timer,pomodoro,pyspt,productivity
Classifier: Development Status :: 4 - Beta
Classifier: Environment :: Console :: Curses
Classifier: Intended Audience :: Developers
Classifier: Intended Audience :: End Users/Desktop
Classifier: Topic :: Utilities
Classifier: License :: OSI Approved :: MIT License
Classifier: Natural Language :: English
Classifier: Programming Language :: Python :: 3.5
Classifier: Programming Language :: Python :: 3.6
Classifier: Programming Language :: Python :: 3.7
Classifier: Programming Language :: Python :: 3.8
Classifier: Programming Language :: Python :: 3.9
Classifier: Programming Language :: Python :: 3.10
Classifier: Programming Language :: Python :: 3 :: Only
Requires-Python: >=3.5, <4
License-File: LICENSE
